Metadata-Version: 2.1
Name: aicore-hangman
Version: 0.0.3
Summary: Corrects the hangman code
Author: Ivan Ying
License: UNKNOWN
Platform: UNKNOWN
